shabd/__init__.py
shabd/shabd.py
shabd-1.1.dist-info/licenses/LICENSE
shabd-1.1.dist-info/METADATA
shabd-1.1.dist-info/WHEEL
shabd-1.1.dist-info/entry_points.txt
shabd-1.1.dist-info/top_level.txt
shabd-1.1.dist-info/RECORD
