Metadata-Version: 2.4
Name: shabd
Version: 1.1
Summary: A command-line English dictionary tool
Home-page: https://github.com/spignelon/shabd
Author: Ujjawal Saini
Author-email: spignelon@proton.me
License: GPL-3.0
Classifier: Development Status :: 3 - Alpha
Classifier: Intended Audience :: End Users/Desktop
Classifier: License :: OSI Approved :: GNU General Public License v3 (GPLv3)
Classifier: Programming Language :: Python :: 3.9
Classifier: Programming Language :: Python :: 3.10
Classifier: Programming Language :: Python :: 3.11
Classifier: Programming Language :: Python :: 3.12
Classifier: Topic :: Education
Classifier: Topic :: Utilities
Requires-Python: >=3.9
License-File: LICENSE
Requires-Dist: beautifulsoup4==4.13.4
Requires-Dist: certifi==2025.4.26
Requires-Dist: charset-normalizer==3.4.2
Requires-Dist: idna==3.10
Requires-Dist: requests==2.32.4
Requires-Dist: soupsieve==2.7
Requires-Dist: typing_extensions==4.14.0
Requires-Dist: urllib3==2.4.0
Dynamic: author
Dynamic: author-email
Dynamic: classifier
Dynamic: description
Dynamic: description-content-type
Dynamic: home-page
Dynamic: license
Dynamic: license-file
Dynamic: requires-dist
Dynamic: requires-python
Dynamic: summary
